setup.py
timing_test/__init__.py
timing_test.egg-info/PKG-INFO
timing_test.egg-info/SOURCES.txt
timing_test.egg-info/dependency_links.txt
timing_test.egg-info/entry_points.txt
timing_test.egg-info/top_level.txt