Metadata-Version: 1.0
Name: timing-test
Version: 0
Summary: 获取任意时间/获取当前的时间戳/时间转时间戳/时间戳转时间
Home-page: https://github.com/sherrrrryy/get_time_tryy
Author: sherrryy
Author-email: yingshiyu519@163.com
License: UNKNOWN
Platform: UNKNOWN
